system_sounds/__init__.py
system_sounds-0.1.1.dist-info/LICENSE
system_sounds-0.1.1.dist-info/METADATA
system_sounds-0.1.1.dist-info/WHEEL
system_sounds-0.1.1.dist-info/RECORD
