Metadata-Version: 2.1
Name: system-sounds
Version: 0.1.1
Summary: list available system sound files
Home-page: https://pypi.org/project/system-sounds/
License: MIT
Keywords: system-sounds,audio-playback,cross-platform,music,sounds,system-music,user-music,sound-library,audio-library
Author: Mark Parker
Author-email: mark@parker-programs.com
Requires-Python: >=3.10,<4.0
Classifier: License :: OSI Approved :: MIT License
Classifier: Programming Language :: Python :: 3
Classifier: Programming Language :: Python :: 3.10
Classifier: Programming Language :: Python :: 3.11
Project-URL: Documentation, https://github.com/MarkParker5/system-sounds/blob/master/README.md
Project-URL: Repository, https://github.com/MarkParker5/system-sounds
